datadog_api_client/__init__.py
datadog_api_client/api_client.py
datadog_api_client/configuration.py
datadog_api_client/exceptions.py
datadog_api_client/model_utils.py
datadog_api_client/py.typed
datadog_api_client/rest.py
datadog_api_client/version.py
datadog_api_client/v1/__init__.py
datadog_api_client/v1/api/__init__.py
datadog_api_client/v1/api/authentication_api.py
datadog_api_client/v1/api/aws_integration_api.py
datadog_api_client/v1/api/aws_logs_integration_api.py
datadog_api_client/v1/api/azure_integration_api.py
datadog_api_client/v1/api/dashboard_lists_api.py
datadog_api_client/v1/api/dashboards_api.py
datadog_api_client/v1/api/downtimes_api.py
datadog_api_client/v1/api/events_api.py
datadog_api_client/v1/api/gcp_integration_api.py
datadog_api_client/v1/api/hosts_api.py
datadog_api_client/v1/api/ip_ranges_api.py
datadog_api_client/v1/api/key_management_api.py
datadog_api_client/v1/api/logs_api.py
datadog_api_client/v1/api/logs_indexes_api.py
datadog_api_client/v1/api/logs_pipelines_api.py
datadog_api_client/v1/api/metrics_api.py
datadog_api_client/v1/api/monitors_api.py
datadog_api_client/v1/api/notebooks_api.py
datadog_api_client/v1/api/organizations_api.py
datadog_api_client/v1/api/pager_duty_integration_api.py
datadog_api_client/v1/api/security_monitoring_api.py
datadog_api_client/v1/api/service_checks_api.py
datadog_api_client/v1/api/service_level_objective_corrections_api.py
datadog_api_client/v1/api/service_level_objectives_api.py
datadog_api_client/v1/api/slack_integration_api.py
datadog_api_client/v1/api/snapshots_api.py
datadog_api_client/v1/api/synthetics_api.py
datadog_api_client/v1/api/tags_api.py
datadog_api_client/v1/api/usage_metering_api.py
datadog_api_client/v1/api/users_api.py
datadog_api_client/v1/api/webhooks_integration_api.py
datadog_api_client/v1/apis/__init__.py
datadog_api_client/v1/model/__init__.py
datadog_api_client/v1/model/access_role.py
datadog_api_client/v1/model/add_signal_to_incident_request.py
datadog_api_client-2.11.0.dist-info/LICENSE
datadog_api_client-2.11.0.dist-info/LICENSE-3rdparty.csv
datadog_api_client-2.11.0.dist-info/METADATA
datadog_api_client-2.11.0.dist-info/NOTICE
datadog_api_client-2.11.0.dist-info/WHEEL
datadog_api_client-2.11.0.dist-info/top_level.txt
datadog_api_client-2.11.0.dist-info/RECORD
