Metadata-Version: 2.1
Name: datadog-api-client
Version: 2.11.0
Summary: Collection of all Datadog Public endpoints
Home-page: https://github.com/DataDog/datadog-api-client-python
Author: Datadog, Inc.
Author-email: packages@datadoghq.com
License: BSD
Project-URL: Bug Tracker, https://github.com/DataDog/datadog-api-client-python/issues
Project-URL: Documentation, https://docs.datadoghq.com/api/
Project-URL: Source Code, https://github.com/DataDog/datadog-api-client-python
Keywords: openapi,api,client,openapi-generator,datadog
Platform: any
Classifier: Intended Audience :: Developers
Classifier: License :: OSI Approved :: BSD License
Classifier: Operating System :: OS Independent
Classifier: Programming Language :: Python :: 3.7
Classifier: Programming Language :: Python :: 3.8
Classifier: Programming Language :: Python :: 3.9
Classifier: Programming Language :: Python :: 3.10
Requires-Python: >=3.7
License-File: LICENSE
License-File: LICENSE-3rdparty.csv
License-File: NOTICE
Requires-Dist: urllib3 (>=1.15)
Requires-Dist: certifi
Requires-Dist: python-dateutil
Requires-Dist: typing-extensions
Provides-Extra: apm
Requires-Dist: ddtrace (>=1.2.0) ; extra == 'apm'
Provides-Extra: async
Requires-Dist: aiosonic ; extra == 'async'
Provides-Extra: tests
Requires-Dist: aiosonic ; extra == 'tests'
Requires-Dist: glom ; extra == 'tests'
Requires-Dist: jinja2 ; extra == 'tests'
Requires-Dist: pytest ; extra == 'tests'
Requires-Dist: pytest-bdd (==6.0.1) ; extra == 'tests'
Requires-Dist: pytest-asyncio ; extra == 'tests'
Requires-Dist: pytest-randomly ; extra == 'tests'
Requires-Dist: pytest-recording ; extra == 'tests'
Requires-Dist: python-dateutil ; extra == 'tests'
Requires-Dist: mypy ; extra == 'tests'
Requires-Dist: types-python-dateutil ; extra == 'tests'
Requires-Dist: zstandard ; extra == 'tests'
Provides-Extra: zstandard
Requires-Dist: zstandard ; extra == 'zstandard'
